reactivity.py
reactivity-0.0.1.dist-info/METADATA
reactivity-0.0.1.dist-info/WHEEL
reactivity-0.0.1.dist-info/top_level.txt
reactivity-0.0.1.dist-info/RECORD
