Metadata-Version: 2.1
Name: reactivity
Version: 0.0.1
Summary: a python vesion vue/reactivity api
Home-page: UNKNOWN
License: UNKNOWN
Platform: UNKNOWN
